sa2django/__init__.py
sa2django/column_mappers.py
sa2django/core.py
sa2django-0.2.1.dist-info/LICENSE
sa2django-0.2.1.dist-info/WHEEL
sa2django-0.2.1.dist-info/METADATA
sa2django-0.2.1.dist-info/RECORD
