Metadata-Version: 2.1
Name: sa2django
Version: 0.2.1
Summary: Convert sqlalchemy database schemas to django database models at runtime.
Home-page: https://github.com/mariushelf/sa2django
License: MIT
Author: Marius Helf
Author-email: helfsmarius@gmail.com
Requires-Python: >=3.6,<4.0
Classifier: Development Status :: 4 - Beta
Classifier: Framework :: Django
Classifier: Framework :: Django :: 3.1
Classifier: License :: OSI Approved :: MIT License
Classifier: Programming Language :: Python :: 3
Classifier: Programming Language :: Python :: 3.6
Classifier: Programming Language :: Python :: 3.7
Classifier: Programming Language :: Python :: 3.8
Classifier: Programming Language :: Python :: 3.9
Classifier: Programming Language :: Python :: Implementation :: PyPy
Requires-Dist: SQLAlchemy-Utils (>=0.36.8,<0.37.0)
Requires-Dist: django (>=3.1.1,<4.0.0)
Requires-Dist: psycopg2 (>=2.8.6,<3.0.0)
Requires-Dist: sqlalchemy (>=1.3,<1.4)
Requires-Dist: sqlalchemy-citext (>=1.7.0,<2.0.0)
Project-URL: Documentation, https://github.com/mariushelf/sa2django
Project-URL: Repository, https://github.com/mariushelf/sa2django
